<?xml version="1.0" encoding="UTF-8" standalone="yes"?>
<service xmlns="http://www.activegrid.com/namespaces/ServiceDefinitions/1.0" id="DB" type="DataService" springFile="DB.spring.xml">
    <dataobjects>
        <dataobject javaType="com.testissue.db.Table1">
            <element name="id" typeRef="java.lang.Integer" isList="false" allowNull="false"/>
            <element name="column2" typeRef="java.lang.Integer" isList="false" allowNull="true"/>
            <element name="column3" typeRef="java.lang.Integer" isList="false" allowNull="true"/>
        </dataobject>
        <dataobject javaType="com.testissue.db.Table2">
            <element name="id" typeRef="java.lang.Integer" isList="false" allowNull="false"/>
            <element name="column2" typeRef="java.lang.Integer" isList="false" allowNull="true"/>
        </dataobject>
    </dataobjects>
</service>
